meta.py
notifier.py
replicator.py
replicator_cli-0.0.7.dist-info/LICENSE
replicator_cli-0.0.7.dist-info/METADATA
replicator_cli-0.0.7.dist-info/WHEEL
replicator_cli-0.0.7.dist-info/entry_points.txt
replicator_cli-0.0.7.dist-info/top_level.txt
replicator_cli-0.0.7.dist-info/RECORD
