Metadata-Version: 2.1
Name: replicator-cli
Version: 0.0.7
Summary: Task runner for backups
Home-page: https://github.com/vitonsky/replicator
Author: Robert Vitonsky
Author-email: rob@vitonsky.net
License: MIT
Classifier: Programming Language :: Python :: 3.8
Classifier: Operating System :: OS Independent
Requires-Python: >=3.7
License-File: LICENSE
Requires-Dist: python-telegram-bot (==20.3)
Requires-Dist: PyYAML (==6.0)
